<annotation>
	<folder>train</folder>
	<filename>image_122.jpg</filename>
	<path>C:\Users\Radhe Raman Tiwari\Pictures\image\train\image_122.jpg</path>
	<source>
		<database>Unknown</database>
	</source>
	<size>
		<width>912</width>
		<height>1024</height>
		<depth>3</depth>
	</size>
	<segmented>0</segmented>
	<object>
		<name>Weed</name>
		<pose>Unspecified</pose>
		<truncated>0</truncated>
		<difficult>0</difficult>
		<bndbox>
			<xmin>708</xmin>
			<ymin>316</ymin>
			<xmax>899</xmax>
			<ymax>597</ymax>
		</bndbox>
	</object>
	<object>
		<name>Weed</name>
		<pose>Unspecified</pose>
		<truncated>0</truncated>
		<difficult>0</difficult>
		<bndbox>
			<xmin>677</xmin>
			<ymin>849</ymin>
			<xmax>892</xmax>
			<ymax>983</ymax>
		</bndbox>
	</object>
	<object>
		<name>Weed</name>
		<pose>Unspecified</pose>
		<truncated>0</truncated>
		<difficult>0</difficult>
		<bndbox>
			<xmin>603</xmin>
			<ymin>728</ymin>
			<xmax>728</xmax>
			<ymax>850</ymax>
		</bndbox>
	</object>
</annotation>
